{
    "locations": {
        "US": {
            "regions": {
                "US-CT": "Connecticut",
                "US-WA": "Washington",
                "US-KS": "Kansas",
                "US-WI": "Wisconsin",
                "US-OR": "Oregon",
                "US-KY": "Kentucky",
                "US-CO": "Colorado",
                "US-OH": "Ohio",
                "US-ME": "Maine",
                "US-MD": "Maryland",
                "US-MA": "Massachusetts",
                "US-AL": "Alabama",
                "US-MO": "Missouri",
                "US-MN": "Minnesota",
                "US-CA": "California",
                "US-OK": "Oklahoma",
                "US-MS": "Mississippi",
                "US-SC": "Sør-Carolina",
                "US-RI": "Rhode Island",
                "US-AR": "Arkansas"
            },
            "name": "forente stater"
        },
        "SK": {
            "name": "Slovakia"
        },
        "SI": {
            "name": "Slovenia"
        },
        "UA": {
            "name": "Ukraina"
        },
        "MX": {
            "name": "Mexico"
        },
        "SE": {
            "name": "Sverige"
        },
        "GB": {
            "name": "Storbritannia"
        }
    }
}